mevo/__init__.py
mevo/mtype.py
mevo/utils.py
mevo/chromosomes/__init__.py
mevo/chromosomes/chromosome.py
mevo/chromosomes/initializers/__init__.py
mevo/chromosomes/initializers/base.py
mevo/chromosomes/initializers/const.py
mevo/chromosomes/initializers/rand_int.py
mevo/chromosomes/initializers/rand_norm.py
mevo/chromosomes/initializers/rand_order.py
mevo/chromosomes/initializers/rand_uniform.py
mevo/individuals/__init__.py
mevo/individuals/base.py
mevo/individuals/es.py
mevo/individuals/ga.py
mevo/population/__init__.py
mevo/population/base.py
mevo/population/es/__init__.py
mevo/population/es/net.py
mevo/population/ga/__init__.py
mevo/population/ga/base.py
mevo/population/ga/float.py
mevo/population/ga/int.py
mevo/population/ga/net.py
mevo/population/ga/order.py
mevo-0.0.2.dist-info/LICENSE
mevo-0.0.2.dist-info/METADATA
mevo-0.0.2.dist-info/WHEEL
mevo-0.0.2.dist-info/top_level.txt
mevo-0.0.2.dist-info/RECORD
