Metadata-Version: 2.1
Name: mevo
Version: 0.0.2
Summary: Evolutionary Algorithms in Python
Home-page: https://github.com/MorvanZhou/mevo
Author: MorvanZhou
Author-email: morvanzhou@hotmail.com
Project-URL: Bug Tracker, https://github.com/MorvanZhou/mevo/issues
Project-URL: Source, https://github.com/MorvanZhou/mevo
Classifier: Programming Language :: Python :: 3
Classifier: License :: OSI Approved :: MIT License
Classifier: Operating System :: OS Independent
Requires-Python: >=3.8
License-File: LICENSE
Requires-Dist: numpy (>=1.20.0)
Provides-Extra: build
Requires-Dist: tox (==3.24.3) ; extra == 'build'
Requires-Dist: tox-conda ; extra == 'build'
Requires-Dist: build ; extra == 'build'
Requires-Dist: twine ; extra == 'build'
Requires-Dist: pylint ; extra == 'build'
Provides-Extra: test
Requires-Dist: gymnasium[classic_control] (>=0.27.1) ; extra == 'test'
